flask_jwt_auth/__init__.py
flask_jwt_auth-0.0.10.dist-info/LICENSE
flask_jwt_auth-0.0.10.dist-info/METADATA
flask_jwt_auth-0.0.10.dist-info/WHEEL
flask_jwt_auth-0.0.10.dist-info/top_level.txt
flask_jwt_auth-0.0.10.dist-info/RECORD
