Metadata-Version: 2.1
Name: flask-jwt-auth
Version: 0.0.10
Summary: This module contains a simple class to implement authentication and authorization in a Flask app using JSON Web Token (JWT)
Home-page: https://github.com/Quakingaspen-codehub/flask_jwt_auth
Author: Quaking Aspen
Author-email: info@quakingaspen.net
License: MIT
Platform: UNKNOWN
Classifier: Programming Language :: Python :: 3
Classifier: License :: OSI Approved :: MIT License
Classifier: Operating System :: OS Independent
Requires-Python: >=3.6
License-File: LICENSE
Requires-Dist: http-status-code (>=0.0.10)
Requires-Dist: SQLAlchemy (>=1.0.0)
